lokisapi/__init__.py
lokisapi/async_client.py
lokisapi/async_model_cache.py
lokisapi/async_utils.py
lokisapi/batch_utils.py
lokisapi/client.py
lokisapi/config.py
lokisapi/exceptions.py
lokisapi/logging_config.py
lokisapi/model_cache.py
lokisapi/models.py
lokisapi/models_config.py
lokisapi/utils.py
lokisapi/validators.py
lokisapi/cache/__init__.py
lokisapi/cache/async_model_cache.py
lokisapi/cache/sync_model_cache.py
lokisapi/clients/__init__.py
lokisapi/clients/async_client.py
lokisapi/clients/sync_client.py
lokisapi-1.1.0.dist-info/licenses/LICENSE
tests/__init__.py
tests/test_client.py
tests/test_utils.py
lokisapi-1.1.0.dist-info/METADATA
lokisapi-1.1.0.dist-info/WHEEL
lokisapi-1.1.0.dist-info/top_level.txt
lokisapi-1.1.0.dist-info/RECORD
